pysmarty/__init__.py
pysmarty/connection.py
pysmarty/exceptions.py
pysmarty/smarty.py
pysmarty/registers/__init__.py
pysmarty/registers/baseregister.py
pysmarty/registers/coil.py
pysmarty/registers/coils.json
pysmarty/registers/discrete_input.py
pysmarty/registers/discrete_inputs.json
pysmarty/registers/holding_register.py
pysmarty/registers/holding_registers.json
pysmarty/registers/input_register.py
pysmarty/registers/input_registers.json
pysmarty/registers/registers.py
pysmarty-0.7-py3.6.egg-info/PKG-INFO
pysmarty-0.7-py3.6.egg-info/SOURCES.txt
pysmarty-0.7-py3.6.egg-info/dependency_links.txt
pysmarty-0.7-py3.6.egg-info/requires.txt
pysmarty-0.7-py3.6.egg-info/top_level.txt
pysmarty-0.8.dist-info/LICENSE
pysmarty-0.8.dist-info/METADATA
pysmarty-0.8.dist-info/WHEEL
pysmarty-0.8.dist-info/top_level.txt
pysmarty-0.8.dist-info/RECORD
